django_postgres_pgpfields/__init__.py
django_postgres_pgpfields/fields.py
django_postgres_pgpfields/managers.py
django_postgres_pgpfields/mixins.py
django_postgres_pgpfields/models.py
django_postgres_pgpfields/proxy.py
django_postgres_pgpfields/migrations/0001_add_pgcrypto_extension.py
django_postgres_pgpfields/migrations/__init__.py
django_postgres_pgpfields-0.0.1.dist-info/DESCRIPTION.rst
django_postgres_pgpfields-0.0.1.dist-info/METADATA
django_postgres_pgpfields-0.0.1.dist-info/metadata.json
django_postgres_pgpfields-0.0.1.dist-info/RECORD
django_postgres_pgpfields-0.0.1.dist-info/top_level.txt
django_postgres_pgpfields-0.0.1.dist-info/WHEEL
tests/__init__.py
tests/factories.py
tests/models.py
tests/run.py
tests/test_fields.py
