Metadata-Version: 2.0
Name: django-postgres-pgpfields
Version: 0.0.1
Summary: PGP encrypted fields, which are encrypted by the pgcrypto postgres extension.
Home-page: https://github.com/coldmind/django-postgres-pgpfields
Author: coldmind
Author-email: me@asokolovskiy.com
License: MIT
Keywords: pgcrypto,pgp,encryption,django,fields
Platform: UNKNOWN
Classifier: Development Status :: 4 - Beta
Classifier: Framework :: Django
Classifier: Intended Audience :: Developers
Classifier: License :: OSI Approved :: BSD License
Classifier: Natural Language :: English
Classifier: Programming Language :: Python :: 2.7
Classifier: Programming Language :: Python :: 3.4
Classifier: Topic :: Database
Classifier: Topic :: Security :: Cryptography
